PlasiaCorrelationProfiler/PlasiaCorrelationProfiler.py
PlasiaCorrelationProfiler/__init__.py
PlasiaCorrelationProfiler/data/Synthetic Benchmark Dataset GSE13898/Barretts.csv
PlasiaCorrelationProfiler/data/Synthetic Benchmark Dataset GSE13898/Normal.csv
PlasiaCorrelationProfiler/data/Synthetic Benchmark Dataset GSE13898/Normal_Barretts.csv
PlasiaCorrelationProfiler/data/Synthetic Benchmark Dataset GSE13898/Normal_StageI.csv
PlasiaCorrelationProfiler/data/Synthetic Benchmark Dataset GSE13898/Normal_StageII.csv
PlasiaCorrelationProfiler/data/Synthetic Benchmark Dataset GSE13898/Normal_StageIII.csv
PlasiaCorrelationProfiler/data/Synthetic Benchmark Dataset GSE13898/P_Normal_StageIII.csv
PlasiaCorrelationProfiler/data/Synthetic Benchmark Dataset GSE13898/StageI.csv
PlasiaCorrelationProfiler/data/Synthetic Benchmark Dataset GSE13898/StageII.csv
PlasiaCorrelationProfiler/data/Synthetic Benchmark Dataset GSE13898/StageIII.csv
PlasiaCorrelationProfiler-0.1.6.dist-info/METADATA
PlasiaCorrelationProfiler-0.1.6.dist-info/WHEEL
PlasiaCorrelationProfiler-0.1.6.dist-info/top_level.txt
PlasiaCorrelationProfiler-0.1.6.dist-info/RECORD
